vk2gpz/__init__.py
vk2gpz/geom/__init__.py
vk2gpz/geom/manifold.py
vk2gpz/geom/util.py
vk2gpz/geom/vertex.py
vk2gpz/geom/grid/__init__.py
vk2gpz/geom/grid/geodesicdome.py
vk2gpz/geom/grid/plane.py
vk2gpz/geom/projection/__init__.py
vk2gpz/geom/projection/equal_earth.py
vk2gpz/geom/projection/kavrayskiy.py
vk2gpz/geom/projection/projection.py
vk2gpz/geom/projection/wagner.py
vk_pygeom-1.0.5.dist-info/LICENSE.txt
vk_pygeom-1.0.5.dist-info/METADATA
vk_pygeom-1.0.5.dist-info/WHEEL
vk_pygeom-1.0.5.dist-info/top_level.txt
vk_pygeom-1.0.5.dist-info/RECORD
