Metadata-Version: 2.1
Name: vk_pygeom
Version: 1.0.5
Summary: This is a collection of geometry related python packages
Author-email: vk2gpz <vk2gpz@gmail.com>
Project-URL: Homepage, https://github.com/vk2gpz/vk_pygeom
Project-URL: Issues, https://github.com/vk2gpz/vk_pygeom/issues
Classifier: Programming Language :: Python :: 3
Classifier: Operating System :: OS Independent
Requires-Python: >=3.8
License-File: LICENSE.txt
